{"Pa\u00eds":"United Kingdom","Monto Total":7285024.6440000003}
{"Pa\u00eds":"Netherlands","Monto Total":285446.34}
{"Pa\u00eds":"EIRE","Monto Total":265262.46}
{"Pa\u00eds":"Germany","Monto Total":228678.4}
{"Pa\u00eds":"France","Monto Total":208934.31}
{"Pa\u00eds":"Australia","Monto Total":138453.81}
{"Pa\u00eds":"Spain","Monto Total":61558.56}
{"Pa\u00eds":"Switzerland","Monto Total":56443.95}
{"Pa\u00eds":"Belgium","Monto Total":41196.34}
{"Pa\u00eds":"Sweden","Monto Total":38367.83}
{"Pa\u00eds":"Japan","Monto Total":37416.37}
{"Pa\u00eds":"Norway","Monto Total":36165.44}
{"Pa\u00eds":"Portugal","Monto Total":33375.84}
{"Pa\u00eds":"Finland","Monto Total":22546.08}
{"Pa\u00eds":"Singapore","Monto Total":21279.29}
{"Pa\u00eds":"Channel Islands","Monto Total":20440.54}
{"Pa\u00eds":"Denmark","Monto Total":18955.34}
{"Pa\u00eds":"Italy","Monto Total":17483.24}
{"Pa\u00eds":"Cyprus","Monto Total":13502.85}
{"Pa\u00eds":"Austria","Monto Total":10198.68}
{"Pa\u00eds":"Poland","Monto Total":7334.65}
{"Pa\u00eds":"Israel","Monto Total":7215.84}
{"Pa\u00eds":"Greece","Monto Total":4760.52}
{"Pa\u00eds":"Iceland","Monto Total":4310.0}
{"Pa\u00eds":"Canada","Monto Total":3666.38}
{"Pa\u00eds":"USA","Monto Total":3580.39}
{"Pa\u00eds":"Malta","Monto Total":2725.59}
{"Pa\u00eds":"Other","Monto Total":2660.77}
{"Pa\u00eds":"United Arab Emirates","Monto Total":1902.28}
{"Pa\u00eds":"Lebanon","Monto Total":1693.88}
{"Pa\u00eds":"Lithuania","Monto Total":1661.06}
{"Pa\u00eds":"European Community","Monto Total":1300.25}
{"Pa\u00eds":"Brazil","Monto Total":1143.6}
{"Pa\u00eds":"RSA","Monto Total":1002.31}
{"Pa\u00eds":"Czech Republic","Monto Total":826.74}
{"Pa\u00eds":"Bahrain","Monto Total":548.4}
{"Pa\u00eds":"Saudi Arabia","Monto Total":145.92}
{"Pa\u00eds":"Hong Kong","Monto Total":0.0}
